ogc_legends.py
ogc_legends-0.1.4.dist-info/LICENSE
ogc_legends-0.1.4.dist-info/METADATA
ogc_legends-0.1.4.dist-info/WHEEL
ogc_legends-0.1.4.dist-info/entry_points.txt
ogc_legends-0.1.4.dist-info/top_level.txt
ogc_legends-0.1.4.dist-info/RECORD
