Metadata-Version: 2.1
Name: ogc-legends
Version: 0.1.4
Summary: A small library to work with OGC legends
Home-page: http://github.com/geographika/ogc-legends
Author: Seth Girvin
Author-email: sethg@geographika.co.uk
License: MIT
Platform: UNKNOWN
Classifier: Development Status :: 3 - Alpha
Classifier: License :: OSI Approved :: MIT License
Classifier: Programming Language :: Python :: 3.6
Classifier: Programming Language :: Python :: 3.7
Classifier: Programming Language :: Python :: 3.8
Classifier: Intended Audience :: Developers
Classifier: Topic :: Software Development :: Build Tools
Requires-Dist: owslib
